odoo/addons/account_receipt_journal/README.rst
odoo/addons/account_receipt_journal/__init__.py
odoo/addons/account_receipt_journal/__manifest__.py
odoo/addons/account_receipt_journal/i18n/account_receipt_journal.pot
odoo/addons/account_receipt_journal/i18n/es.po
odoo/addons/account_receipt_journal/i18n/it.po
odoo/addons/account_receipt_journal/migrations/18.0.1.0.3/pre-migrate.py
odoo/addons/account_receipt_journal/models/__init__.py
odoo/addons/account_receipt_journal/models/account_chart_template.py
odoo/addons/account_receipt_journal/models/account_journal.py
odoo/addons/account_receipt_journal/models/account_move.py
odoo/addons/account_receipt_journal/readme/CONTRIBUTORS.md
odoo/addons/account_receipt_journal/readme/DESCRIPTION.md
odoo/addons/account_receipt_journal/readme/HISTORY.md
odoo/addons/account_receipt_journal/readme/ROADMAP.md
odoo/addons/account_receipt_journal/static/description/icon.png
odoo/addons/account_receipt_journal/static/description/index.html
odoo/addons/account_receipt_journal/tests/__init__.py
odoo/addons/account_receipt_journal/tests/test_receipts.py
odoo/addons/account_receipt_journal/views/account_journal_views.xml
odoo_addon_account_receipt_journal-18.0.1.1.0.1.dist-info/METADATA
odoo_addon_account_receipt_journal-18.0.1.1.0.1.dist-info/WHEEL
odoo_addon_account_receipt_journal-18.0.1.1.0.1.dist-info/top_level.txt
odoo_addon_account_receipt_journal-18.0.1.1.0.1.dist-info/RECORD
