Metadata-Version: 2.1
Name: odoo-addon-account_receipt_journal
Version: 18.0.1.1.0.1
Requires-Python: >=3.10
Requires-Dist: odoo==18.0.*
Requires-Dist: openupgradelib
Summary: Define and use journals dedicated to receipts
Home-page: https://github.com/OCA/account-invoicing
License: LGPL-3
Author: TAKOBI, Odoo Community Association (OCA)
Author-email: support@odoo-community.org
Classifier: Programming Language :: Python
Classifier: Framework :: Odoo
Classifier: Framework :: Odoo :: 18.0
Classifier: License :: OSI Approved :: GNU Lesser General Public License v3 (LGPLv3)
Classifier: Development Status :: 4 - Beta
